pincho/__init__.py
pincho/async_client.py
pincho/client.py
pincho/crypto.py
pincho/exceptions.py
pincho/models.py
pincho/py.typed
pincho/validation.py
pincho_sdk-1.0.0a6.dist-info/licenses/LICENSE
pincho_sdk-1.0.0a6.dist-info/METADATA
pincho_sdk-1.0.0a6.dist-info/WHEEL
pincho_sdk-1.0.0a6.dist-info/top_level.txt
pincho_sdk-1.0.0a6.dist-info/RECORD
